setup.cfg
setup.py
squmfit/__init__.py
squmfit/expr.py
squmfit/fit.py
squmfit/parameter.py
squmfit/plot.py
squmfit/pretty.py
squmfit.egg-info/PKG-INFO
squmfit.egg-info/SOURCES.txt
squmfit.egg-info/dependency_links.txt
squmfit.egg-info/requires.txt
squmfit.egg-info/top_level.txt