Metadata-Version: 1.1
Name: squmfit
Version: 0.1
Summary: Convenient non-linear least squares fitting
Home-page: http://github.com/bgamari/squmfit
Author: Ben Gamari
Author-email: ben@smart-cactus.org
License: BSD
Platform: UNKNOWN
Classifier: Development Status :: 3 - Alpha
Classifier: License :: OSI Approved :: MIT License
Classifier: Programming Language :: Python :: 2
Classifier: Programming Language :: Python :: 2.6
Classifier: Programming Language :: Python :: 2.7
Classifier: Programming Language :: Python :: 3
Classifier: Programming Language :: Python :: 3.2
Classifier: Programming Language :: Python :: 3.3
Classifier: Programming Language :: Python :: 3.4
